url/__init__.py
url/__init__.pyi
url/py.typed
url/url.cp314t-win32.pyd
url_py-0.18.0.dist-info/METADATA
url_py-0.18.0.dist-info/WHEEL
url_py-0.18.0.dist-info/licenses/LICENSE
url_py-0.18.0.dist-info/RECORD
