Metadata-Version: 2.4
Name: url-py
Version: 0.18.0
Classifier: Development Status :: 3 - Alpha
Classifier: Intended Audience :: Developers
Classifier: License :: OSI Approved :: MIT License
Classifier: Operating System :: OS Independent
Classifier: Programming Language :: Rust
Classifier: Programming Language :: Python :: 3.9
Classifier: Programming Language :: Python :: 3.10
Classifier: Programming Language :: Python :: 3.11
Classifier: Programming Language :: Python :: 3.12
Classifier: Programming Language :: Python :: 3.13
Classifier: Programming Language :: Python :: 3.14
Classifier: Programming Language :: Python :: 3
Classifier: Programming Language :: Python :: Implementation :: CPython
Classifier: Programming Language :: Python :: Implementation :: PyPy
License-File: LICENSE
Summary: Python bindings to Rust's url crate (from Servo)
Keywords: data structures,rust,persistent
Author-email: Julian Berman <Julian+url-py@GrayVines.com>
Requires-Python: >=3.9
Project-URL: Documentation, https://url-py.readthedocs.io/
Project-URL: Homepage, https://github.com/crate-py/url
Project-URL: Issues, https://github.com/crate-py/url/issues/
Project-URL: Funding, https://github.com/sponsors/Julian
Project-URL: Source, https://github.com/crate-py/url
